securefields/__init__.py
django_securefields-0.0.1.dist-info/LICENSE
django_securefields-0.0.1.dist-info/METADATA
django_securefields-0.0.1.dist-info/WHEEL
django_securefields-0.0.1.dist-info/top_level.txt
django_securefields-0.0.1.dist-info/RECORD
