Metadata-Version: 2.1
Name: django-securefields
Version: 0.0.1
Summary: A Django module for managing secure database model fields.
Home-page: https://github.com/fivehealth/django-securefields
Author: 5 Health Inc
Author-email: hello@botmd.io
License: MIT License
Keywords: django security encryption hashing hmac aes
Platform: UNKNOWN
Classifier: Development Status :: 2 - Pre-Alpha
Classifier: Programming Language :: Python :: 3
Classifier: Framework :: Django
Classifier: Framework :: Django :: 2.2
Classifier: Framework :: Django :: 3.0
Classifier: Framework :: Django :: 3.1
Classifier: License :: OSI Approved :: MIT License
Requires-Python: >=3
Requires-Dist: django (>=2.2)
Requires-Dist: cryptography (>=2.9)
